{
	"$schema": "https://raw.githubusercontent.com/googleapis/release-please/main/schemas/config.json",
	"description": "Auto-Generated Release Please configuration for prerelease",
	"pull-request-title-pattern": "chore: prerelease release prepared",
	"pull-request-header": "chore: prerelease release prepared",
	"pull-request-footer": "This PR was generated by the prepare-release GHA",
	"release-type": "node",
	"versioning": "prerelease",
	"prerelease": true,
	"prerelease-type": "next",
	"packages": {
		"apps/ts-to-openapi": {
			"package-name": "ts-to-openapi",
			"changelog-path": "docs/changelog.md",
			"extra-files": ["src/cli.ts", "tests/cli.spec.ts", "src/index.ts"]
		},
		"apps/ts-to-schema": {
			"package-name": "ts-to-schema",
			"changelog-path": "docs/changelog.md",
			"extra-files": ["src/cli.ts", "tests/cli.spec.ts", "src/index.ts"]
		}
	},
	"plugins": [
		"node-workspace",
		{
			"type": "linked-versions",
			"groupName": "repo",
			"components": ["ts-to-openapi", "ts-to-schema"]
		}
	]
}
